[
  {
    "ContainingType": "OrderService.Controllers.OrdersController",
    "Method": "CreateOrder",
    "RelativePath": "Orders",
    "HttpMethod": "POST",
    "IsController": true,
    "Order": 0,
    "Parameters": [
      {
        "Name": "createOrder",
        "Type": "OrderService.DTOs.CreateOrderDto",
        "IsRequired": true
      }
    ],
    "ReturnTypes": []
  },
  {
    "ContainingType": "OrderService.Controllers.OrdersController",
    "Method": "GetOrderById",
    "RelativePath": "Orders/{id}",
    "HttpMethod": "GET",
    "IsController": true,
    "Order": 0,
    "Parameters": [
      {
        "Name": "id",
        "Type": "System.Guid",
        "IsRequired": true
      }
    ],
    "ReturnTypes": [
      {
        "Type": "OrderService.DTOs.OrderDto",
        "MediaTypes": [
          "text/plain",
          "application/json",
          "text/json"
        ],
        "StatusCode": 200
      }
    ]
  },
  {
    "ContainingType": "OrderService.Controllers.OrdersController",
    "Method": "GetAllOrders",
    "RelativePath": "Orders/orders",
    "HttpMethod": "GET",
    "IsController": true,
    "Order": 0,
    "Parameters": [],
    "ReturnTypes": [
      {
        "Type": "System.Collections.Generic.List\u00601[[OrderService.DTOs.OrderDto, OrderService, Version=1.0.0.0, Culture=neutral, PublicKeyToken=null]]",
        "MediaTypes": [
          "text/plain",
          "application/json",
          "text/json"
        ],
        "StatusCode": 200
      }
    ]
  }
]